{
    "http": {
        "header": {
            "Content-Type": "text/html; charset=utf-8",
            "Transfer-Encoding": "chunked",
            "Connection": "keep-alive",
            "Cache-Control": "public, max-age=300, must-revalidate",
            "Date": "Wed, 16 Sep 2020 10:00:55 GMT",
            "ETag": "W/\"203d3-zOSlQPD3psF8miTxmz4+ok8T4D8\"",
            "Strict-Transport-Security": "max-age=15552000",
            "X-Frame-Options": "sameorigin",
            "X-XSS-Protection": "1",
            "Content-Encoding": "gzip",
            "Vary": "Accept-Encoding",
            "X-Cache": "Hit from cloudfront",
            "Via": "1.1 8c73194b247676a80d86714cba2447a5.cloudfront.net (CloudFront)",
            "X-Amz-Cf-Pop": "SIN52-C3",
            "X-Amz-Cf-Id": "jSoCU0jZ9-4gVjRMz7JH5GccIzSBfy2ybzwq2z0XO8dtm4ld91iTnA==",
            "Age": "97"
        },
        "nslookup": {
            "smallpdf.com": [
                "13.227.248.137"
            ]
        },
        "ping": {
            "smallpdf.com": [
                "13.227.248.137"
            ]
        },
        "CNAME": {
            "smallpdf.com": "still a low_level domain_name"
        },
        "A": {
            "smallpdf.com": "still a low_level domain_name"
        }
    },
    "https": {
        "header": {
            "Content-Type": "text/html; charset=utf-8",
            "Transfer-Encoding": "chunked",
            "Connection": "keep-alive",
            "Cache-Control": "public, max-age=300, must-revalidate",
            "Date": "Wed, 16 Sep 2020 10:00:55 GMT",
            "ETag": "W/\"203d3-zOSlQPD3psF8miTxmz4+ok8T4D8\"",
            "Strict-Transport-Security": "max-age=15552000",
            "X-Frame-Options": "sameorigin",
            "X-XSS-Protection": "1",
            "Content-Encoding": "gzip",
            "Vary": "Accept-Encoding",
            "X-Cache": "Hit from cloudfront",
            "Via": "1.1 322d4a6b5dc93fed92dc98b4eacf25ca.cloudfront.net (CloudFront)",
            "X-Amz-Cf-Pop": "SIN52-C3",
            "X-Amz-Cf-Id": "zroTbVPQyVg8UDIOX3hq2E0hQrUQ9FvHz17SuKesZIWFaiEC1C7qPw==",
            "Age": "97"
        },
        "nslookup": {
            "smallpdf.com": [
                "13.227.248.137"
            ]
        },
        "ping": {
            "smallpdf.com": [
                "13.227.248.137"
            ]
        },
        "CNAME": {
            "smallpdf.com": "still a low_level domain_name"
        },
        "A": {
            "smallpdf.com": "still a low_level domain_name"
        }
    }
}