{
    "http": null,
    "https": {
        "header": {
            "Content-Type": "text/html; charset=us-ascii",
            "Server": "Microsoft-HTTPAPI/2.0",
            "Date": "Thu, 17 Sep 2020 05:47:30 GMT",
            "Connection": "close",
            "Content-Length": "315"
        },
        "nslookup": {
            "nicvpn-cmcc.sjtu.edu.cn": [
                "202.120.2.37"
            ]
        },
        "ping": {
            "nicvpn-cmcc.sjtu.edu.cn": [
                "202.120.2.37"
            ]
        },
        "CNAME": {
            "nicvpn-cmcc.sjtu.edu.cn": [
                "nicvpn-edu.sjtu.edu.cn."
            ]
        },
        "A": {
            "nicvpn-cmcc.sjtu.edu.cn": [
                "202.120.2.37"
            ]
        }
    }
}